dist
eigen
pyoptools
scripts
