Metadata-Version: 2.4
Name: pyoptools
Version: 0.3.7
Summary: Python tools for simulation of optical systems
Author-email: Ricardo Amézquita Orozco <ramezquitao@cihologramas.com>
License:                     GNU GENERAL PUBLIC LICENSE
License-File: LICENSE.txt
Requires-Dist: numpy>=1.26.2
Requires-Dist: scipy>=1.5.2
Requires-Dist: imageio>=2.9.0
Requires-Dist: PyYAML>=5.3.1
Requires-Dist: matplotlib>=3.3.1
Requires-Dist: orjson>=3.10.7
Requires-Dist: Pillow>=10.0.1
Requires-Dist: importlib-resources>=3.3.0
Provides-Extra: test
Requires-Dist: pytest>=8.2.1; extra == "test"
Requires-Dist: pytest-cov>=5.0.0; extra == "test"
Dynamic: license-file
